Metadata-Version: 2.1
Name: crypt_r
Version: 3.13.0
Summary: A copy of the `crypt` module that was removed in Python 3.13
Author-email: "Steven D. Majewski" <sdm7g@virginia.edu>
Maintainer-email: Miro Hrončok <miro@hroncok.cz>, Petr Viktorin <encukou@gmail.com>, Tomáš Hrnčiar <tomas.hrnciar@me.com>, Karolina Surma <ksurma@redhat.com>
License: A. HISTORY OF THE SOFTWARE
Project-URL: Homepage, https://github.com/fedora-python/crypt_r
Project-URL: Bug Tracker, https://github.com/fedora-python/crypt_r/issues
Classifier: Programming Language :: Python :: 3
Classifier: Programming Language :: Python :: Implementation :: CPython
Classifier: License :: OSI Approved :: Python Software Foundation License
Classifier: Operating System :: POSIX :: Linux
Requires-Python: >=3.11
License-File: LICENSE
